logparser/__init__.py
logparser/version.py
logparser/AEL/AEL.py
logparser/AEL/__init__.py
logparser/AEL/benchmark.py
logparser/AEL/demo.py
logparser/Drain/Drain.py
logparser/Drain/__init__.py
logparser/Drain/benchmark.py
logparser/Drain/demo.py
logparser/IPLoM/IPLoM.py
logparser/IPLoM/__init__.py
logparser/IPLoM/benchmark.py
logparser/IPLoM/demo.py
logparser/LFA/LFA.py
logparser/LFA/__init__.py
logparser/LFA/benchmark.py
logparser/LFA/demo.py
logparser/LKE/LKE.py
logparser/LKE/__init__.py
logparser/LKE/benchmark.py
logparser/LKE/demo.py
logparser/LenMa/__init__.py
logparser/LenMa/benchmark.py
logparser/LenMa/demo.py
logparser/LenMa/src/LenMa.py
logparser/LenMa/src/__init__.py
logparser/LenMa/src/lenma_template.py
logparser/LenMa/src/template.py
logparser/LogCluster/__init__.py
logparser/LogCluster/benchmark.py
logparser/LogCluster/demo.py
logparser/LogCluster/src/LogCluster.py
logparser/LogCluster/src/__init__.py
logparser/LogMine/__init__.py
logparser/LogMine/benchmark.py
logparser/LogMine/demo.py
logparser/LogMine/src/LogMine.py
logparser/LogMine/src/__init__.py
logparser/LogMine/src/alignment.py
logparser/LogSig/LogSig.py
logparser/LogSig/__init__.py
logparser/LogSig/benchmark.py
logparser/LogSig/demo.py
logparser/MoLFI/__init__.py
logparser/MoLFI/benchmark.py
logparser/MoLFI/demo.py
logparser/MoLFI/src/MoLFI.py
logparser/MoLFI/src/__init__.py
logparser/MoLFI/src/definitions.py
logparser/MoLFI/src/validation.py
logparser/MoLFI/src/main/__init__.py
logparser/MoLFI/src/main/org/__init__.py
logparser/MoLFI/src/main/org/core/__init__.py
logparser/MoLFI/src/main/org/core/chromosome/__init__.py
logparser/MoLFI/src/main/org/core/chromosome/chromosome.py
logparser/MoLFI/src/main/org/core/chromosome/template.py
logparser/MoLFI/src/main/org/core/fitness/__init__.py
logparser/MoLFI/src/main/org/core/fitness/objectives2D.py
logparser/MoLFI/src/main/org/core/metaheuristics/NSGA_II_2D.py
logparser/MoLFI/src/main/org/core/metaheuristics/__init__.py
logpai-1.0.0.dist-info/LICENSE
logpai-1.0.0.dist-info/METADATA
logpai-1.0.0.dist-info/WHEEL
logpai-1.0.0.dist-info/top_level.txt
logpai-1.0.0.dist-info/RECORD
