Metadata-Version: 2.1
Name: logpai
Version: 1.0.0
Summary: Log Analytics Powered by AI
Home-page: https://github.com/logpai/logparser
Author: logpai
Author-email: logpai@users.noreply.github.com
License: Apache-2.0 License
Download-URL: https://github.com/logpai/logparser/tags
Keywords: log analysis,log parsing,AIOps
Platform: UNKNOWN
Classifier: License :: OSI Approved :: Apache Software License
Classifier: Operating System :: OS Independent
Classifier: Intended Audience :: Developers
Classifier: Intended Audience :: Education
Classifier: Intended Audience :: Science/Research
Classifier: Programming Language :: Python :: 3
Classifier: Programming Language :: Python :: 3.7
Classifier: Topic :: Scientific/Engineering
Classifier: Topic :: Scientific/Engineering :: Artificial Intelligence
Classifier: Topic :: Software Development
Classifier: Topic :: Software Development :: Libraries
Classifier: Topic :: Software Development :: Libraries :: Python Modules
Requires-Python: >=3.6
